nanocube/__init__.py
nanocube/nano_cube.py
nanocube/nano_index.py
nanocube/schema.py
tests/test_nanocube.py
nanocube-0.2.1.dist-info/LICENSE
nanocube-0.2.1.dist-info/METADATA
nanocube-0.2.1.dist-info/WHEEL
nanocube-0.2.1.dist-info/top_level.txt
nanocube-0.2.1.dist-info/zip-safe
nanocube-0.2.1.dist-info/RECORD
