Metadata-Version: 2.1
Name: nanocube
Version: 0.2.1
Summary: Lightning fast OLAP-style point queries on Pandas DataFrames.
Home-page: https://github.com/Zeutschler/nanocube
Author: Thomas Zeutschler
Author-email: cubedpandas@gmail.com
Maintainer-email: Thomas Zeutschler <cubedpandas@gmail.com>
License: MIT License
Project-URL: Homepage, https://github.com/Zeutschler/nanocube
Project-URL: Documentation, https://github.com/Zeutschler/nanocube
Project-URL: Repository, https://github.com/Zeutschler/nanocube.git
Project-URL: Issues, https://github.com/Zeutschler/nanocube/issues
Project-URL: pypi, https://pypi.org/project/nanocube/
Keywords: python,pandas,numpy,spark,data analysis,OLAP,cube,dataframe
Platform: any
Classifier: Intended Audience :: Science/Research
Classifier: Intended Audience :: Developers
Classifier: License :: OSI Approved :: MIT License
Classifier: Development Status :: 5 - Production/Stable
Classifier: Programming Language :: Python :: 3.9
Classifier: Programming Language :: Python :: 3.10
Classifier: Programming Language :: Python :: 3.11
Classifier: Programming Language :: Python :: 3.12
Classifier: Programming Language :: Python :: 3.13
Classifier: Topic :: Software Development
Classifier: Topic :: Scientific/Engineering
Classifier: Operating System :: Microsoft :: Windows
Classifier: Operating System :: POSIX
Classifier: Operating System :: Unix
Classifier: Operating System :: MacOS
Requires-Python: >= 3.10
License-File: LICENSE
Requires-Dist: numpy
Requires-Dist: pandas
Requires-Dist: pyroaring
Requires-Dist: pyarrow
Requires-Dist: sortednp
Requires-Dist: lz4
Requires-Dist: zstandard
